spoti_dl-2.1.2.dist-info/METADATA
spoti_dl-2.1.2.dist-info/WHEEL
spoti_dl-2.1.2.dist-info/entry_points.txt
spoti_dl-2.1.2.dist-info/license_files/LICENSE
spotidl/config.py
spotidl/__init__.py
spotidl/cli.py
spotidl/utils.py
spotidl/main.py
spotidl/spotify.py
spotidl/spotidl_rs.pyd
spoti_dl-2.1.2.dist-info/RECORD
