Metadata-Version: 2.3
Name: spoti-dl
Version: 2.1.2
Classifier: Programming Language :: Rust
Classifier: Programming Language :: Python :: Implementation :: CPython
Classifier: Programming Language :: Python :: Implementation :: PyPy
Classifier: Topic :: Multimedia :: Sound/Audio
Classifier: Environment :: Console
Requires-Dist: spotipy ==2.23.0
Requires-Dist: python-dotenv ==1.0.0
Requires-Dist: yt-dlp >=2024.5.27
Requires-Dist: black ; extra == 'dev'
Requires-Dist: pytest ; extra == 'test'
Provides-Extra: dev
Provides-Extra: test
License-File: LICENSE
Summary: spoti-dl: download songs, albums and playlists using Spotify links
Author: Dhruv Ahuja
Requires-Python: >=3.8
Project-URL: repository, https://github.com/dhruv-ahuja/spoti-dl/
